Metadata-Version: 2.1
Name: nonebot-plugin-weather-lite
Version: 0.0.1
Summary: 使用wttr.in的天气查询 ，支持大部分wttr.in的用法。
Home-page: https://github.com/zjkwdy/nonebot_plugin_weather_lite
Author: zjkwdy
Author-email: 3377911508@qq.com
License: UNKNOWN
Keywords: pip,nonebot2,nonebot,weather,nonebot_plugin
Platform: any
Classifier: Programming Language :: Python :: 3
Classifier: License :: OSI Approved :: MIT License
Classifier: Operating System :: OS Independent
License-File: LICENSE
Requires-Dist: nonebot2 (>=2.0.0b1)
Requires-Dist: nonebot-adapter-onebot (>=2.0.0b1)
